ud_ted/CostModel.py
ud_ted/__init__.py
ud_ted/cli.py
ud_ted/distance.py
ud_ted/uted.py
ud_ted-0.1.0.dist-info/LICENSE.md
ud_ted-0.1.0.dist-info/METADATA
ud_ted-0.1.0.dist-info/WHEEL
ud_ted-0.1.0.dist-info/entry_points.txt
ud_ted-0.1.0.dist-info/top_level.txt
ud_ted-0.1.0.dist-info/RECORD
