Metadata-Version: 2.1
Name: ud-ted
Version: 0.1.0
Summary: A tree edit-distance tool for Universal Dependencies.
Home-page: https://github.com/breaklikeafish/UD-TED
Author: Klara Lennermann
Author-email: breaklikeafish@gmail.com
Project-URL: Bug Tracker, https://github.com/breaklikeafish/UD-TED/issues
Classifier: Programming Language :: Python :: 3
Classifier: License :: OSI Approved :: GNU General Public License v3 (GPLv3)
Classifier: Operating System :: OS Independent
License-File: LICENSE.md
Requires-Dist: edist
Requires-Dist: numpy (>=1.20)
Requires-Dist: pyconll
